docker_mounter/mounter.py
docker_mounter-0.1.0.dist-info/LICENSE
docker_mounter-0.1.0.dist-info/METADATA
docker_mounter-0.1.0.dist-info/WHEEL
docker_mounter-0.1.0.dist-info/entry_points.txt
docker_mounter-0.1.0.dist-info/RECORD
