Metadata-Version: 2.1
Name: docker-mounter
Version: 0.1.0
Summary: Utility to mount Docker images locally without requiring container creation
License: MIT
Author: Joseph Redfern
Author-email: joseph@redfern.me
Requires-Python: >=3.11,<4.0
Classifier: License :: OSI Approved :: MIT License
Classifier: Programming Language :: Python :: 3
Classifier: Programming Language :: Python :: 3.11
Classifier: Programming Language :: Python :: 3.12
Requires-Dist: docker (>=7.1.0,<8.0.0)
Requires-Dist: loguru (>=0.7.3,<0.8.0)
Requires-Dist: typer (>=0.15.1,<0.16.0)
